cb2325_numerica_g8-0.2.1.dist-info/licenses/LICENSE
cb2325numericag8/__init__.py
cb2325numericag8/aproximacao/__init__.py
cb2325numericag8/aproximacao/minimos_quadrados.py
cb2325numericag8/aproximacao/regressao_linear.py
cb2325numericag8/erros/__init__.py
cb2325numericag8/erros/erros.py
cb2325numericag8/grafico/__init__.py
cb2325numericag8/grafico/grafico_ajuste_linear.py
cb2325numericag8/grafico/grafico_integracao.py
cb2325numericag8/grafico/grafico_interpolacao_hermite.py
cb2325numericag8/grafico/grafico_interpolacao_newton.py
cb2325numericag8/grafico/grafico_interpolador_linear_por_partes.py
cb2325numericag8/grafico/grafico_minimos_quadrados.py
cb2325numericag8/grafico/grafico_raizes.py
cb2325numericag8/integracao/__init__.py
cb2325numericag8/integracao/integracao.py
cb2325numericag8/interpolacao/__init__.py
cb2325numericag8/interpolacao/interpolador_hermite.py
cb2325numericag8/interpolacao/interpolador_linear_por_partes.py
cb2325numericag8/interpolacao/interpolador_polinomial.py
cb2325numericag8/raizes/__init__.py
cb2325numericag8/raizes/raizes.py
cb2325numericag8/utils/__init__.py
cb2325numericag8/utils/kahan.py
cb2325_numerica_g8-0.2.1.dist-info/METADATA
cb2325_numerica_g8-0.2.1.dist-info/WHEEL
cb2325_numerica_g8-0.2.1.dist-info/top_level.txt
cb2325_numerica_g8-0.2.1.dist-info/RECORD
