Metadata-Version: 2.4
Name: cb2325-numerica-g8
Version: 0.2.1
Summary: Ferramentas de Cálculo Numérico (interpolação, raízes, integração, etc.)
Author-email: AllanYukio <al.allan.furuhashi@impatech.edu.br>, dulce-costa <al.dulce.costa@impatech.edu.br>, AFelipeL <al.felipe.oliveira@impatech.edu.br>, heitor-brazuna <al.heitor.brazuna@impatech.edu.br>, ingrid-s-c <al.ingrid.carvalho@impatech.edu.br>, joserafael1981 <al.jose.melo@impatech.edu.br>, lazyluca <al.luca.fujii@impatech.edu.br>, LuisFelipeM777 <al.luis.luna@impatech.edu.br>, marceloavlopes <al.marcelo.lopes@impatech.edu.br>, altiagoribeiro <al.tiago.ribeiro@impatech.edu.br>
License: MIT License
Project-URL: Homepage, https://github.com/lazyluca/CB2325NumericaG8
Classifier: Programming Language :: Python :: 3
Classifier: License :: OSI Approved :: MIT License
Classifier: Operating System :: OS Independent
Requires-Python: >=3.9
License-File: LICENSE
Requires-Dist: numpy>=1.26
Requires-Dist: matplotlib>=3.10
Provides-Extra: dev
Requires-Dist: pytest; extra == "dev"
Dynamic: license-file
